[
  {
    "empId": 1007,
    "firstName": "Johann",
    "lastName": "Bach",
    "toDo": [],
    "done": []
  },
  {
    "empId": 1008,
    "firstName": "Ally",
    "lastName": "Hingtgen",
    "toDo": [],
    "done": []
  },
  {
    "empId": 1009,
    "firstName": "Harper",
    "lastName": "Hingtgen",
    "toDo": [],
    "done": []
  },
  {
    "empId": 1010,
    "firstName": "Bella",
    "lastName": "Sue",
    "toDo": [],
    "done": []
  },
  {
    "empId": 1011,
    "firstName": "Paige",
    "lastName": "Catherine",
    "toDo": [],
    "done": []
  },
  {
    "empId": 1012,
    "firstName": "Chris",
    "lastName": "Prior",
    "toDo": [],
    "done": []
  }
]
